gcloud_requests/__init__.py
gcloud_requests/credentials_watcher.py
gcloud_requests/datastore.py
gcloud_requests/proxy.py
gcloud_requests/pubsub.py
gcloud_requests/storage.py
gcloud_requests-2.0.4.dist-info/LICENSE
gcloud_requests-2.0.4.dist-info/METADATA
gcloud_requests-2.0.4.dist-info/WHEEL
gcloud_requests-2.0.4.dist-info/top_level.txt
gcloud_requests-2.0.4.dist-info/RECORD
