Metadata-Version: 2.1
Name: gcloud-requests
Version: 2.0.4
Summary: Thread-safe client functionality for gcloud-python via requests.
Home-page: https://github.com/leadpages/gcloud_requests
Author: Leadpages
Author-email: opensource@leadpages.net
License: MIT
Platform: UNKNOWN
Classifier: Development Status :: 5 - Production/Stable
Classifier: Intended Audience :: Developers
Classifier: Topic :: Software Development :: Libraries
Classifier: License :: OSI Approved :: MIT License
Classifier: Programming Language :: Python :: 2
Classifier: Programming Language :: Python :: 2.7
Classifier: Programming Language :: Python :: 3.5
Classifier: Programming Language :: Python :: 3.6
Classifier: Programming Language :: Python :: 3.7
Classifier: Programming Language :: Python :: 3.8
Requires-Dist: google-auth (<2.0,>=1.0.1)
Requires-Dist: google-cloud-core (<2.0,>=0.25)
Requires-Dist: requests (<3,>=2.9)
Requires-Dist: six (<2.0,>=1.10.0)
